simplelinks/__init__.py
simplelinks/cli.py
simplelinks/client.py
simplelinks/client_v3.py
simplelinks/database.py
simplelinks/rate_limiter.py
simplelinks/server.py
simplelinks/tcp_p2p.py
simplelinks/utils.py
simplelinks/web_api.py
simplelinks-3.1.3.dist-info/licenses/LICENSE
simplelinks-3.1.3.dist-info/METADATA
simplelinks-3.1.3.dist-info/WHEEL
simplelinks-3.1.3.dist-info/entry_points.txt
simplelinks-3.1.3.dist-info/top_level.txt
simplelinks-3.1.3.dist-info/RECORD
